assistant/__init__.py
assistant/__main__.py
assistant/_execer.py
assistant/as_client.py
assistant/as_service.py
assistant/builtin_cmds.py
assistant/codecache.py
assistant/conditions.py
assistant/execer.py
assistant/history.py
assistant/icons.py
assistant/main.py
assistant/parser.py
assistant/time.py
assistant/utils.py
assistant/version.py
assistant/vocabulary.py
assistant/api/responses.py
assistant/entry_points/__init__.py
assistant/entry_points/run_assistant.py
assistant/listen/__init__.py
assistant/listen/__main__.py
assistant/listen/interface.py
assistant/listen/main.py
assistant/manager/__init__.py
assistant/manager/__main__.py
assistant/manager/nlu.py
assistant/manager/nlu_to_stt.py
assistant/nlp/__init__.py
assistant/nlp/clear.py
assistant/nlp/exit.py
assistant/nlp/interface.py
assistant/nlp/think.py
assistant/nlp/chains/__init__.py
assistant/nlp/chains/__main__.py
assistant/nlp/chains/code_pilot.py
assistant/nlp/chains/docs_explained.py
assistant/nlp/chains/persistent_session.py
assistant/nlp/chains/session.py
assistant/nlp/chains/agents/__executor__.py
assistant/nlp/chains/agents/__init__.py
assistant/nlp/chains/agents/assistant.py
assistant/nlp/chains/callback_handlers/__init__.py
assistant/nlp/chains/data_loaders/__init__.py
assistant/nlp/chains/data_splitter/__init__.py
assistant/nlp/chains/embeddings/__init__.py
assistant/nlp/chains/embeddings/assistant.py
assistant/nlp/chains/memory/__init__.py
assistant/nlp/chains/memory/conversation_buffer.py
assistant/nlp/chains/models/__init__.py
assistant/nlp/chains/models/hf.py
assistant/nlp/chains/models/vllm.py
assistant/nlp/chains/parsers/__init__.py
assistant/nlp/chains/parsers/column_csv.py
assistant/nlp/chains/parsers/json.py
assistant/nlp/chains/parsers/markdown_json.py
assistant/nlp/chains/prompts/__init__.py
assistant/nlp/chains/prompts/airoboros.py
assistant/nlp/chains/prompts/json.py
assistant/nlp/chains/schema/__init__.py
assistant/nlp/chains/schema/memory.py
assistant/nlp/chains/schema/vectorstore.py
assistant-1.2.1b1.dist-info/LICENSE
assistant-1.2.1b1.dist-info/METADATA
assistant-1.2.1b1.dist-info/WHEEL
assistant-1.2.1b1.dist-info/entry_points.txt
assistant-1.2.1b1.dist-info/top_level.txt
assistant-1.2.1b1.dist-info/RECORD
