Metadata-Version: 2.1
Name: assistant
Version: 1.2.1b1
Summary: Your very own Assistant. Because you deserve it.
Home-page: https://gitlab.com/waser-technologies/technologies/assistant
Author: Danny Waser
Author-email: danny@waser.tech
License: MIT
Project-URL: Documentation, https://gitlab.com/waser-technologies/technologies/assistant/blob/master/README.md
Project-URL: Code, https://gitlab.com/waser-technologies/technologies/assistant
Project-URL: Issue tracker, https://gitlab.com/waser-technologies/technologies/assistant/issues
Platform: any
Classifier: Programming Language :: Python :: 3
Classifier: Programming Language :: Python :: 3.8
Classifier: Programming Language :: Python :: 3.9
Classifier: Programming Language :: Python :: 3.10
Classifier: Programming Language :: Python :: 3.11
Classifier: License :: OSI Approved :: MIT License
Classifier: Operating System :: OS Independent
Classifier: Natural Language :: English
Classifier: Natural Language :: French
Classifier: Topic :: System :: Shells
Classifier: Programming Language :: Unix Shell
Classifier: Topic :: Terminals
Requires-Python: >=3.8,<4
License-File: LICENSE
Requires-Dist: ftfy
Requires-Dist: pydub
Requires-Dist: pygments
Requires-Dist: xonsh
Requires-Dist: prompt-toolkit >3.0.36
Requires-Dist: attrs
Requires-Dist: questionary
Requires-Dist: datasets
Requires-Dist: transformers
Requires-Dist: sentencepiece
Requires-Dist: sentence-transformers
Requires-Dist: bitsandbytes
Requires-Dist: accelerate
Requires-Dist: peft
Requires-Dist: einops
Requires-Dist: langchain
Requires-Dist: langchain-community
Requires-Dist: websockets
Requires-Dist: colorama
Requires-Dist: rich
Requires-Dist: halo
Requires-Dist: duckduckgo-search ==5.3.1b1
Requires-Dist: wikipedia
Requires-Dist: pexpect
Requires-Dist: scipy
Requires-Dist: chromadb
Requires-Dist: pydantic <2.0
Requires-Dist: fsspec >=2023.10.0
